midb/__init__.py
midb_gossrock-0.0.4.dist-info/LICENSE
midb_gossrock-0.0.4.dist-info/METADATA
midb_gossrock-0.0.4.dist-info/WHEEL
midb_gossrock-0.0.4.dist-info/top_level.txt
midb_gossrock-0.0.4.dist-info/RECORD
